{
    "task_id": "P3-SDK-05",
    "status": "success",
    "execution_mode": "Serial-Batching",
    "timestamp": "2025-12-15T14:15:00+08:00",
    "modified_files": [
        "exo-sdk/src/instructions/escrow.ts",
        "exo-sdk/src/index.ts"
    ],
    "verification": {
        "unit": {
            "command": "cd exo-sdk && pnpm run typecheck",
            "exit_code": 0,
            "output_snippet": "> @exo/sdk@0.1.0 typecheck\n> tsc --noEmit\n\nNo errors"
        },
        "build": {
            "command": "cd exo-sdk && pnpm run build",
            "exit_code": 0,
            "output_snippet": "> @exo/sdk@0.1.0 build\n\nCJS dist/index.js\nESM dist/index.mjs\nDTS dist/index.d.mts"
        }
    },
    "diagnostics_log": [],
    "acceptance_criteria": {
        "AC-01": {
            "description": "Escrow 指令文件 exo-sdk/src/instructions/escrow.ts 存在",
            "status": "PASS",
            "evidence": "File created with 458 lines, exporting 4 functions + 1 class"
        },
        "AC-02": {
            "description": "TypeScript 编译通过 (无错误)",
            "status": "PASS",
            "evidence": "pnpm run typecheck exit_code=0, pnpm run build exit_code=0"
        }
    },
    "deliverables": {
        "escrow.ts": {
            "path": "exo-sdk/src/instructions/escrow.ts",
            "exports": [
                "CreateEscrowArgs",
                "FundEscrowArgs",
                "ReleaseEscrowArgs",
                "CreateEscrowAccounts",
                "FundEscrowAccounts",
                "ReleaseEscrowAccounts",
                "CancelEscrowAccounts",
                "createEscrow",
                "fundEscrow",
                "releaseEscrow",
                "cancelEscrow",
                "EscrowInstructionBuilder"
            ],
            "description": "Escrow 托管操作指令构建器 - 创建/注资/释放/取消"
        }
    },
    "checkpoint": {
        "step": 4,
        "total_steps": 4,
        "last_modified": [
            "exo-sdk/src/instructions/escrow.ts",
            "exo-sdk/src/index.ts"
        ]
    },
    "note_to_csa": "Escrow 客户端实现完成，包含四个核心指令构建器函数和一个便捷类。discriminator 使用占位符，待 IDL 部署后更新。"
}